LICENSE
fsai_shared_funcs/__init__.py
fsai_shared_funcs/conversion_helper.py
fsai_shared_funcs/database_helpers/contextmanagers.py
fsai_shared_funcs/database_helpers/functions.py
fsai_shared_funcs/dict_helper.py
fsai_shared_funcs/elastic_helpers/batch_manager.py
fsai_shared_funcs/elastic_helpers/functions.py
fsai_shared_funcs/file_helper.py
fsai_shared_funcs/geo_helper.py
fsai_shared_funcs/grpc_helpers/contextmanagers.py
fsai_shared_funcs/grpc_helpers/decorators.py
fsai_shared_funcs/grpc_helpers/functions.py
fsai_shared_funcs/int_helper.py
fsai_shared_funcs/json_helper.py
fsai_shared_funcs/kafka_helpers/__init__.py
fsai_shared_funcs/kafka_helpers/sasl_config.py
fsai_shared_funcs/proto_helpers/__init__.py
fsai_shared_funcs/proto_helpers/decorators.py
fsai_shared_funcs/proto_helpers/functions.py
fsai_shared_funcs/proto_helpers/json_format.py
fsai_shared_funcs/redis_helpers/decorators.py
fsai_shared_funcs/redis_helpers/functions.py
fsai_shared_funcs/storage_helper.py
fsai_shared_funcs/string_helper.py
fsai_shared_funcs/time_helper.py
fsai_shared_funcs-0.0.261.dist-info/LICENSE
fsai_shared_funcs-0.0.261.dist-info/METADATA
fsai_shared_funcs-0.0.261.dist-info/WHEEL
fsai_shared_funcs-0.0.261.dist-info/RECORD
