Metadata-Version: 2.1
Name: fsai-shared-funcs
Version: 0.0.261
Summary: Simple functions shared across fsai apps.
Home-page: https://github.com/fsai-dev/fsai-cli-tools
License: MIT
Author: Michael Mohamed
Author-email: michael@foundationstack.com
Requires-Python: >=3.9,<4.0
Classifier: License :: OSI Approved :: MIT License
Classifier: Programming Language :: Python :: 3
Classifier: Programming Language :: Python :: 3.9
Classifier: Programming Language :: Python :: 3.10
Classifier: Programming Language :: Python :: 3.11
Classifier: Programming Language :: Python :: 3.12
Requires-Dist: asyncio (>=3.4.3,<4.0.0)
Requires-Dist: beartype (>=0.16.4,<0.17.0)
Requires-Dist: boto3 (>=1.34.159,<2.0.0)
Requires-Dist: google (>=3.0.0,<4.0.0)
Requires-Dist: jsonlines (>=3.1.0,<4.0.0)
Requires-Dist: loguru (>=0.6.0,<0.7.0)
Requires-Dist: protobuf (>=4.21.11,<5.0.0)
Requires-Dist: pydash (>=5.1.0,<6.0.0)
Requires-Dist: smart-open (>=7.0.4,<8.0.0)
Requires-Dist: tenacity (>=9.1.2,<10.0.0)
Project-URL: Repository, https://github.com/fsai-dev/fsai-cli-tools
